{
  "main": {
    "id": "e2f12f3c99e230ee",
    "type": "split",
    "children": [
      {
        "id": "c4d27fecaecc60bc",
        "type": "tabs",
        "children": [
          {
            "id": "0424439c19d8a462",
            "type": "leaf",
            "state": {
              "type": "bases",
              "state": {
                "file": "Sem título.base",
                "viewName": "Tabela"
              },
              "icon": "lucide-table",
              "title": "Sem título"
            }
          }
        ]
      }
    ],
    "direction": "vertical"
  },
  "left": {
    "id": "b55736b9f7987b42",
    "type": "split",
    "children": [
      {
        "id": "90230f7143a7f9aa",
        "type": "tabs",
        "children": [
          {
            "id": "565b37838d8935a9",
            "type": "leaf",
            "state": {
              "type": "file-explorer",
              "state": {
                "sortOrder": "alphabetical",
                "autoReveal": false
              },
              "icon": "lucide-folder-closed",
              "title": "Explorador de arquivos"
            }
          },
          {
            "id": "b765ef1537264099",
            "type": "leaf",
            "state": {
              "type": "search",
              "state": {
                "query": "",
                "matchingCase": false,
                "explainSearch": false,
                "collapseAll": false,
                "extraContext": false,
                "sortOrder": "alphabetical"
              },
              "icon": "lucide-search",
              "title": "Procurar"
            }
          },
          {
            "id": "7407bebb08b61082",
            "type": "leaf",
            "state": {
              "type": "bookmarks",
              "state": {},
              "icon": "lucide-bookmark",
              "title": "Marcadores"
            }
          }
        ]
      }
    ],
    "direction": "horizontal",
    "width": 300
  },
  "right": {
    "id": "df0d14a13533c7ce",
    "type": "split",
    "children": [
      {
        "id": "f5a2110c490beb36",
        "type": "tabs",
        "children": [
          {
            "id": "b8a7c10fde272084",
            "type": "leaf",
            "state": {
              "type": "backlink",
              "state": {
                "collapseAll": false,
                "extraContext": false,
                "sortOrder": "alphabetical",
                "showSearch": false,
                "searchQuery": "",
                "backlinkCollapsed": false,
                "unlinkedCollapsed": true
              },
              "icon": "links-coming-in",
              "title": "Links inversos"
            }
          },
          {
            "id": "3870f243fad39104",
            "type": "leaf",
            "state": {
              "type": "outgoing-link",
              "state": {
                "linksCollapsed": false,
                "unlinkedCollapsed": true
              },
              "icon": "links-going-out",
              "title": "Links de saída"
            }
          },
          {
            "id": "d73269873d385341",
            "type": "leaf",
            "state": {
              "type": "tag",
              "state": {
                "sortOrder": "frequency",
                "useHierarchy": true,
                "showSearch": false,
                "searchQuery": ""
              },
              "icon": "lucide-tags",
              "title": "Etiquetas"
            }
          },
          {
            "id": "534e934f58b9f014",
            "type": "leaf",
            "state": {
              "type": "all-properties",
              "state": {
                "sortOrder": "frequency",
                "showSearch": false,
                "searchQuery": ""
              },
              "icon": "lucide-archive",
              "title": "Todas as propriedades"
            }
          },
          {
            "id": "f24f3725f2d4536a",
            "type": "leaf",
            "state": {
              "type": "outline",
              "state": {
                "followCursor": false,
                "showSearch": false,
                "searchQuery": ""
              },
              "icon": "lucide-list",
              "title": "Sumário"
            }
          },
          {
            "id": "4f87c851a5fc3e61",
            "type": "leaf",
            "state": {
              "type": "footnotes",
              "state": {
                "file": "Sem título.base"
              },
              "icon": "lucide-file-signature",
              "title": "Notas de rodapé"
            }
          }
        ]
      }
    ],
    "direction": "horizontal",
    "width": 300,
    "collapsed": true
  },
  "left-ribbon": {
    "hiddenItems": {
      "switcher:Abrir a troca rápida": false,
      "graph:Abrir visualização em gráfico": false,
      "canvas:Criar novo canvas": false,
      "daily-notes:Abrir a nota de hoje": false,
      "templates:Inserir modelo": false,
      "command-palette:Abrir paleta de comandos": false,
      "bases:Criar nova base": false,
      "terminal:Open terminal": false
    }
  },
  "active": "0424439c19d8a462",
  "lastOpenFiles": [
    "Sem título.base",
    "skills-lock.json",
    "Sem título.canvas",
    "Sem título",
    "Sem título 1.base",
    "Sem título.md",
    "Bem-vindo.md"
  ]
}